photohunt/__init__.py
photohunt/__main__.py
photohunt/generate_reports.py
photohunt/html_template.py
photohunt/photohunt.py
photohunt_osint-1.0.2.dist-info/LICENSE
photohunt_osint-1.0.2.dist-info/METADATA
photohunt_osint-1.0.2.dist-info/WHEEL
photohunt_osint-1.0.2.dist-info/entry_points.txt
photohunt_osint-1.0.2.dist-info/top_level.txt
photohunt_osint-1.0.2.dist-info/RECORD
