Metadata-Version: 2.1
Name: photohunt-osint
Version: 1.0.2
Summary: OSINT photo search for people based on Search4Faces
Home-page: https://github.com/IrenicFalcon/photohunt-osint
Author: IrenicFalcon
License: MIT
Keywords: osint photo search4faces search people
Classifier: Programming Language :: Python :: 3
Classifier: License :: OSI Approved :: MIT License
Classifier: Operating System :: OS Independent
Classifier: Framework :: AsyncIO
Requires-Python: >=3.6
License-File: LICENSE
Requires-Dist: httpx
Requires-Dist: jinja2
Requires-Dist: openpyxl
Requires-Dist: aiofiles
Requires-Dist: tqdm
